<annotation>
	<folder>images</folder>
	<filename>dandelion_137.png</filename>
	<path>C:\Users\SerhatTuran\Desktop\flowers_detection\flowers_dataset\yolo_dataset\images\dandelion_137.png</path>
	<source>
		<database>Unknown</database>
	</source>
	<size>
		<width>640</width>
		<height>640</height>
		<depth>3</depth>
	</size>
	<segmented>0</segmented>
	<object>
		<name>dandelion</name>
		<pose>Unspecified</pose>
		<truncated>0</truncated>
		<difficult>0</difficult>
		<bndbox>
			<xmin>189</xmin>
			<ymin>46</ymin>
			<xmax>582</xmax>
			<ymax>607</ymax>
		</bndbox>
	</object>
</annotation>
